fdx_utils.py
method_tree_parser.py
datasources/__init__.py
datasources/datasource.py
fashiondx_lib-0.0.2.dist-info/LICENSE
fashiondx_lib-0.0.2.dist-info/METADATA
fashiondx_lib-0.0.2.dist-info/WHEEL
fashiondx_lib-0.0.2.dist-info/top_level.txt
fashiondx_lib-0.0.2.dist-info/RECORD
