Metadata-Version: 2.1
Name: fashiondx-lib
Version: 0.0.2
Summary: fdx lib
Home-page: https://github.com/FashionDx/fdx-lib
Author: Rakshit Sharma
Author-email: rakshit@fashiondx.co
License: UNKNOWN
Platform: UNKNOWN
Classifier: Programming Language :: Python :: 3
Classifier: License :: OSI Approved :: MIT License
Classifier: Operating System :: OS Independent
Requires-Python: >=3.6
Requires-Dist: numpy
Requires-Dist: pandas
Requires-Dist: pymongo
Requires-Dist: elasticsearch
